LICENSE
MANIFEST.in
README.rst
__init__.py
pyproject.toml
setup.cfg
setup.py
wall_e_models/__init__.py
wall_e_models/customFields.py
wall_e_models/models.py
wall_e_models.egg-info/PKG-INFO
wall_e_models.egg-info/SOURCES.txt
wall_e_models.egg-info/dependency_links.txt
wall_e_models.egg-info/requires.txt
wall_e_models.egg-info/top_level.txt
wall_e_models/migrations/0001_initial.py
wall_e_models/migrations/0002_auto_20220203_2111.py
wall_e_models/migrations/0003_auto_20220204_2003.py
wall_e_models/migrations/0004_auto_20220206_1142.py
wall_e_models/migrations/0005_auto_20220715_1532.py
wall_e_models/migrations/0006_auto_20220909_1633.py
wall_e_models/migrations/0007_auto_20230827_1520.py
wall_e_models/migrations/0008_rename_banrecords_banrecord.py
wall_e_models/migrations/0009_helpmessage.py
wall_e_models/migrations/0010_embedavatar.py
wall_e_models/migrations/0011_auto_20231109_0129.py
wall_e_models/migrations/0012_auto_20231111_0144.py
wall_e_models/migrations/0013_updateduser.py
wall_e_models/migrations/0014_alter_updateduser_user_point.py
wall_e_models/migrations/0015_auto_20231116_1503.py
wall_e_models/migrations/0016_auto_20231117_1840.py
wall_e_models/migrations/0017_auto_20231117_1840.py
wall_e_models/migrations/0018_auto_20231118_1003.py
wall_e_models/migrations/0019_auto_20240114_2025.py
wall_e_models/migrations/0020_banrecord_unique_active_ban.py
wall_e_models/migrations/0021_alter_banrecord_is_purged.py
wall_e_models/migrations/0022_auto_20240115_1602.py
wall_e_models/migrations/0023_auto_20240115_1733.py
wall_e_models/migrations/0024_userpoint_discord_avatar_link_expiry_date.py
wall_e_models/migrations/__init__.py